README.rst
setup.py
gitticket/__init__.py
gitticket/bitbucket.py
gitticket/cmd.py
gitticket/config.py
gitticket/github.py
gitticket/redmine.py
gitticket/ticket.py
gitticket/util.py
gitticket.egg-info/PKG-INFO
gitticket.egg-info/SOURCES.txt
gitticket.egg-info/dependency_links.txt
gitticket.egg-info/entry_points.txt
gitticket.egg-info/not-zip-safe
gitticket.egg-info/requires.txt
gitticket.egg-info/top_level.txt
test/test_config.py
test/test_github.py
test/test_ticket.py