Metadata-Version: 1.0
Name: gitticket
Version: 0.5
Summary: Git and issue tracking system integration
Home-page: https://www.github.com/aflc/git-ticket
Author: Hiroyuki Tanaka
Author-email: aflc0x@gmail.com
License: UNKNOWN
Platform: UNKNOWN
Classifier: Development Status :: 3 - Alpha
Classifier: Environment :: Console
Classifier: Intended Audience :: Developers
Classifier: Natural Language :: English
Classifier: Natural Language :: Japanese
Classifier: License :: OSI Approved :: MIT License
Classifier: Programming Language :: Python :: 2 :: Only
Classifier: Programming Language :: Python
Classifier: Programming Language :: Python :: 2.5
Classifier: Programming Language :: Python :: 2.6
Classifier: Programming Language :: Python :: 2.7
Classifier: Topic :: Software Development :: Bug Tracking
Classifier: Topic :: Software Development :: Version Control
